jubilee/__init__.py
jubilee/app.py
jubilee/base_classes.py
jubilee/misc.py
jubilee/mode_log.py
jubilee/mode_shut_down.py
jubilee/mouse_interface.py
jubilee/touch_interface.py
jubilee/worker.py
jubilee/Examples/Hello/hello.py
jubilee/Examples/Hello/hello_worker.py
jubilee/Examples/Images/images.py
jubilee/Examples/Modes/modes.py
jubilee/Examples/Pointer/pointer.py
jubilee/Examples/Script/script.py
jubilee/Examples/Sound/sound.py
jubilee/Examples/Submodes/submodes.py
jubilee-0.104.dist-info/licenses/LICENSE
jubilee-0.104.dist-info/METADATA
jubilee-0.104.dist-info/WHEEL
jubilee-0.104.dist-info/top_level.txt
jubilee-0.104.dist-info/RECORD
