Metadata-Version: 2.4
Name: jubilee
Version: 0.104
Summary: Lightweight application framework built on pygame
Author-email: David Stein <jubilee@steinemail.com>
License-Expression: GPL-3.0-or-later
License-File: LICENSE
Dynamic: license-file
